pubmed_sdk/__init__.py
pubmed_sdk/pubmed_sdk.py
pubmed_sdk-0.4.data/data/requirements.txt
pubmed_sdk-0.4.dist-info/LICENSE
pubmed_sdk-0.4.dist-info/METADATA
pubmed_sdk-0.4.dist-info/WHEEL
pubmed_sdk-0.4.dist-info/top_level.txt
pubmed_sdk-0.4.dist-info/RECORD
