Metadata-Version: 2.1
Name: pubmed-sdk
Version: 0.4
Summary: A Python SDK for searching PubMed using the NCBI E-Utilities
Home-page: http://github.com/pubmed-ai/pubmed_sdk
Author: Leo Sternlicht
Author-email: lsternlicht@gmail.com
License: MIT
Keywords: pubmed ncbi e-utilities sdk,pubmed api
Classifier: License :: OSI Approved :: MIT License
Classifier: Programming Language :: Python
Classifier: Programming Language :: Python :: 3
Classifier: Programming Language :: Python :: 3.6
Classifier: Programming Language :: Python :: 3.7
Classifier: Programming Language :: Python :: 3.8
Classifier: Programming Language :: Python :: 3.9
Requires-Python: >=3.6
License-File: LICENSE
Requires-Dist: setuptools (>=58.0.4)
Requires-Dist: requests (>=2.26.0)
Requires-Dist: xmltodict (>=0.12.0)
Requires-Dist: pytest (>=7.2.2)
Requires-Dist: ruff (>=0.0.263)
Requires-Dist: pdoc (==13.1.0)
Requires-Dist: pip-audit (>=1.1.0)
